LbRelease/__init__.py
LbRelease/_LHCbDocResources/__init__.py
LbRelease/_LHCbDocResources/class.php
LbRelease/_LHCbDocResources/layout.xml-1.7.2
LbRelease/_LHCbDocResources/layout.xml-1.8.11
LbRelease/_LHCbDocResources/layout.xml-1.8.2
LbRelease/_LHCbDocResources/layout.xml-1.8.9.1
LbReleaseDoxy-0.1.3.dist-info/METADATA
LbReleaseDoxy-0.1.3.dist-info/WHEEL
LbReleaseDoxy-0.1.3.dist-info/top_level.txt
LbReleaseDoxy-0.1.3.dist-info/RECORD
